fixed2float-4.0.1.dist-info/METADATA
fixed2float-4.0.1.dist-info/WHEEL
fixed2float/__init__.py
fixed2float/fixed2float.pyd
fixed2float-4.0.1.dist-info/RECORD
