Metadata-Version: 2.1
Name: fixed2float
Version: 4.0.1
Summary: Fixed point to floating point conversion utility
Keywords: fixed,float,q-format
Author: Francesco Urbani <francescourbanidue@gmail.com>
Author-email: Francesco Urbani <francescourbanidue@gmail.com>
Requires-Python: >=3.7
Project-URL: Source Code, https://github.com/urbanij/fixed2float
